configdir/__init__.py
configdir/compat.py
configdir/exceptions.py
configdir/interpolator.py
configdir/parser.py
configdir-0.3.1.dist-info/LICENSE
configdir-0.3.1.dist-info/WHEEL
configdir-0.3.1.dist-info/METADATA
configdir-0.3.1.dist-info/RECORD
