Metadata-Version: 2.1
Name: configdir
Version: 0.3.1
Summary: File names for keys. File contents for values.
Home-page: https://github.com/plynth/configdir
Author: Michael Thornton
Author-email: six8@devdetails.com
Requires-Python: >=3.6,<4.0
Classifier: Programming Language :: Python :: 3
Classifier: Programming Language :: Python :: 3.6
Classifier: Programming Language :: Python :: 3.7
Classifier: Programming Language :: Python :: 3.8
Classifier: Programming Language :: Python :: 3.9
Classifier: Topic :: Software Development :: Libraries :: Python Modules
Project-URL: Repository, https://github.com/plynth/configdir
